setup.py
wheelcms_disqus/__init__.py
wheelcms_disqus/models.py
wheelcms_disqus.egg-info/PKG-INFO
wheelcms_disqus.egg-info/SOURCES.txt
wheelcms_disqus.egg-info/dependency_links.txt
wheelcms_disqus.egg-info/namespace_packages.txt
wheelcms_disqus.egg-info/not-zip-safe
wheelcms_disqus.egg-info/requires.txt
wheelcms_disqus.egg-info/top_level.txt
wheelcms_disqus/migrations/0001_initial.py
wheelcms_disqus/migrations/__init__.py