Metadata-Version: 1.1
Name: wheelcms-disqus
Version: 1.1
Summary: WheelCMS Disqus comment support
Home-page: http://github.com/wheelcms/wheelcms_disqus
Author: Ivo van der Wijk
Author-email: wheelcms@in.m3r.nl
License: BSD
Platform: UNKNOWN
Classifier: Programming Language :: Python
